{
  "_fv": 57,
  "_type": "recipe",
  "definition": {
    "recipeType": "Smithing",
    "recipeRetstackSize": 1,
    "group": "",
    "cookingBookCategory": "MISC",
    "xpReward": 0.0,
    "cookingTime": 200,
    "craftingBookCategory": "MISC",
    "recipeShapeless": false,
    "smithingInputStack": {
      "value": "CUSTOM:SuperChargedCoil"
    },
    "smithingInputAdditionStack": {
      "value": "CUSTOM:MadrigenSolution"
    },
    "smithingInputTemplateStack": {
      "value": "CUSTOM:AncientTemplate"
    },
    "smithingReturnStack": {
      "value": "CUSTOM:OverChargeCoil"
    },
    "name": "super_charge_coil_r",
    "namespace": "mod"
  }
}